athena_query_lib/__init__.py
athena_query_lib/query_handler.py
athena_query_lib-1.0.2.dist-info/METADATA
athena_query_lib-1.0.2.dist-info/WHEEL
athena_query_lib-1.0.2.dist-info/top_level.txt
athena_query_lib-1.0.2.dist-info/RECORD
